torchrecorder/__init__.py
torchrecorder/helpers.py
torchrecorder/nodes.py
torchrecorder/recorder.py
torchrecorder/renderer/__init__.py
torchrecorder/renderer/base.py
torchrecorder/renderer/gv.py
torchrecorder-1.0.3.dist-info/LICENSE
torchrecorder-1.0.3.dist-info/METADATA
torchrecorder-1.0.3.dist-info/WHEEL
torchrecorder-1.0.3.dist-info/top_level.txt
torchrecorder-1.0.3.dist-info/zip-safe
torchrecorder-1.0.3.dist-info/RECORD
