Metadata-Version: 2.1
Name: torchrecorder
Version: 1.0.3
Summary: Record execution graphs of PyTorch neural networks
Home-page: https://github.com/ahgamut/torchrecorder
Author: Gautham Venkatasubramanian
Author-email: ahgamut@gmail.com
License: MIT
Platform: UNKNOWN
Classifier: Programming Language :: Python :: 3.6
Classifier: Programming Language :: Python :: 3.7
Classifier: Topic :: Scientific/Engineering :: Visualization
Classifier: Intended Audience :: Science/Research
Classifier: License :: OSI Approved :: MIT License
License-File: LICENSE
Requires-Dist: torch (>=1.3)
Requires-Dist: graphviz
